mypypy/__init__.py
mypypy-0.3.0.dist-info/METADATA
mypypy-0.3.0.dist-info/WHEEL
mypypy-0.3.0.dist-info/RECORD
